k8sutils/__init__.py
k8sutils/namespace.py
k8sutils/crds/__init__.py
k8sutils/crds/utils.py
k8sutils/deployments/__init__.py
k8sutils/deployments/utils.py
k8sutils/local/__init__.py
k8sutils/local/minikube.py
k8sutils/pods/__init__.py
k8sutils/pods/utils.py
k8sutils-0.1.3.dist-info/LICENSE
k8sutils-0.1.3.dist-info/METADATA
k8sutils-0.1.3.dist-info/WHEEL
k8sutils-0.1.3.dist-info/top_level.txt
k8sutils-0.1.3.dist-info/RECORD
