Metadata-Version: 2.1
Name: k8sutils
Version: 0.1.3
Summary: Kubernetes helper module for Python
Author-email: Rui Vieira <ruidevieira@googlemail.com>
License: Apache License Version 2.0
Keywords: k8s,kubernetes,utilities
Classifier: Programming Language :: Python
Classifier: Programming Language :: Python :: 3
Requires-Python: >=3.8
License-File: LICENSE
Requires-Dist: requests ==2.28.0
Requires-Dist: termcolor ==1.1.0
Requires-Dist: prettytable ==2.1.0
Requires-Dist: PyYAML ==6.0.1
Requires-Dist: dotty-dict ==1.3.1
Provides-Extra: dev
Requires-Dist: pytest ==6.2.2 ; extra == 'dev'
